mitoc_const/__init__.py
mitoc_const/affiliations.py
mitoc_const/membership.py
mitoc_const/py.typed
mitoc_const-1.0.1.dist-info/LICENSE
mitoc_const-1.0.1.dist-info/METADATA
mitoc_const-1.0.1.dist-info/WHEEL
mitoc_const-1.0.1.dist-info/top_level.txt
mitoc_const-1.0.1.dist-info/RECORD
