Metadata-Version: 2.1
Name: mitoc-const
Version: 1.0.1
Summary: Constants for use across MIT Outing Club infrastructure
Home-page: https://github.com/DavidCain/mitoc-const
Author: David Cain
Author-email: davidjosephcain@gmail.com
License: UNKNOWN
Platform: UNKNOWN
Classifier: Development Status :: 4 - Beta
Classifier: Intended Audience :: Education
Classifier: Programming Language :: Python
Classifier: License :: OSI Approved :: MIT License
Requires-Python: >=3.5
